pypdsadmin/__init__.py
pypdsadmin/commands/__init__.py
pypdsadmin/commands/account/__init__.py
pypdsadmin/commands/account/create.py
pypdsadmin/commands/account/delete.py
pypdsadmin/commands/account/list.py
pypdsadmin/commands/account/reset_password.py
pypdsadmin/commands/account/takedown.py
pypdsadmin/commands/account/untakedown.py
pypdsadmin/commands/account/update_handle.py
pypdsadmin/commands/create_invite_code.py
pypdsadmin/commands/request_crawl.py
pypdsadmin/consts.py
pypdsadmin/env.py
pypdsadmin/lib/__init__.py
pypdsadmin/lib/tokens.py
pypdsadmin/main.py
py_pdsadmin-0.1.0rc0.dist-info/LICENSE
py_pdsadmin-0.1.0rc0.dist-info/METADATA
py_pdsadmin-0.1.0rc0.dist-info/WHEEL
py_pdsadmin-0.1.0rc0.dist-info/entry_points.txt
py_pdsadmin-0.1.0rc0.dist-info/RECORD
